LICENSE
MANIFEST.in
README.rst
requirements.txt
setup.py
breq/__init__.py
breq/breq.py
breq/github.py
breq/guardian.py
breq/reddit.py
breq/wikipedia.py
breq.egg-info/PKG-INFO
breq.egg-info/SOURCES.txt
breq.egg-info/dependency_links.txt
breq.egg-info/requires.txt
breq.egg-info/top_level.txt