Metadata-Version: 1.1
Name: breq
Version: 0.7
Summary: Browse Web service requests.
Home-page: UNKNOWN
Author: Ramiro Gómez
Author-email: code@ramiro.org
License: MIT
Platform: UNKNOWN
Classifier: Development Status :: 4 - Beta
Classifier: Environment :: Console
Classifier: Intended Audience :: Developers
Classifier: License :: OSI Approved :: MIT License
Classifier: Operating System :: POSIX
Classifier: Programming Language :: Python
Classifier: Topic :: Communications
Classifier: Topic :: Text Processing
